phonikud_onnx/__init__.py
phonikud_onnx/model.py
phonikud_onnx/py.typed
phonikud_onnx-1.0.6.dist-info/METADATA
phonikud_onnx-1.0.6.dist-info/WHEEL
phonikud_onnx-1.0.6.dist-info/RECORD
