Metadata-Version: 2.4
Name: phonikud-onnx
Version: 1.0.6
Summary: Add diacritics to Hebrew text along with phonetic marks
Author-email: thewh1teagle <61390950+thewh1teagle@users.noreply.github.com>
Requires-Python: >=3.10
Requires-Dist: onnxruntime>=1.21.1
Requires-Dist: tokenizers>=0.20
